pickle_cache/__init__.py
pickle_cache/lib.py
pickle_cache-0.1.0.dist-info/METADATA
pickle_cache-0.1.0.dist-info/RECORD
pickle_cache-0.1.0.dist-info/WHEEL
pickle_cache-0.1.0.dist-info/top_level.txt
